<dataset type="EDDTableFromNcFiles" datasetID="HakaiSeaspanRoyalSuperCO2Provisional_merged" active="true">
    <reloadEveryNMinutes>10080</reloadEveryNMinutes>
    <updateEveryNMillis>10000</updateEveryNMillis>
    <fileDir>/datasets/HakaiSeaspanRoyalSuperCO2Provisional/processed/super_co2/</fileDir>
    <fileNameRegex>nmea_super_co2.*\.nc</fileNameRegex>
    <recursive>true</recursive>
    <pathRegex>.*</pathRegex>
    <metadataFrom>last</metadataFrom>
    <standardizeWhat>0</standardizeWhat>
    <sortedColumnSourceName>time</sortedColumnSourceName>
    <sortFilesBySourceNames>time</sortFilesBySourceNames>
    <fileTableInMemory>false</fileTableInMemory>
    <addAttributes>
        <att name="_NCProperties">null</att>
        <att name="cdm_data_type">trajectory</att>
        <att name="Conventions">COARDS, CF-1.6, ACDD-1.3</att>
        <att name="infoUrl">???</att>
        <att name="institution">Hakai Institute</att>
        <att name="keywords">820pwr, a_820pwr, abs, air, air_pressure, air_temp, altimetry, atmosphere, atmospheric, b_pressure_bar, b_pressure_inch, barometric, bars, carbon, carbon dioxide, cell, Cell_P, Cell_T, co2, CO2_abs, CO2_ppm, cond, corrected_wind_direction, course, data, degrees, dioxide, direction, doy, earth, Earth Science &gt; Atmosphere &gt; Atmospheric Pressure &gt; Atmospheric Pressure Measurements, Earth Science &gt; Atmosphere &gt; Atmospheric Pressure &gt; Sea Level Pressure, Earth Science &gt; Atmosphere &gt; Atmospheric Pressure &gt; Static Pressure, Earth Science &gt; Atmosphere &gt; Atmospheric Winds &gt; Surface Winds, fluke, Fluke_Temp, global, gps, gps_datetime, ground, H2O_ppt_mass, H2Oabs, heading, inches, io1, io2, io3, knots, laboratory, latitude, level, longitude, mass, measurements, mercury, O2, oabs, over, oxygen, platform, positioning, ppm, ppt, press, Press_kPa, Press_V, pressure, raw, relative, remote, Remote_Therm, sal, satellite, sb63, SB63_O2, SB63_RawP, SB63_RawTV, SB63_T, science, sea, spd_over_grnd, speed, standard, StandardVal, static, surface, system, temperature, therm, time, time_doy_utc, true, true_course, tsg, TSG_Cond, TSG_Sal, TSG_T, underway, v, val, valve1pos, wind, wind_direction_relative_to_platform, wind_from_direction, wind_speed, wind_speed_relative_to_platform_knots, winds, xco2</att>
        <att name="keywords_vocabulary">GCMD Science Keywords</att>
        <att name="license">[standard]</att>
        <att name="sourceUrl">(local files)</att>
        <att name="standard_name_vocabulary">CF Standard Name Table v79</att>
        <att name="subsetVariables">platform_name</att>
        <att name="summary">This is a preliminary dataset.</att>
        <att name="title">Seaspan Royal Surface Underway Super CO2 with weather data</att>
        <att name="cdm_trajectory_variables">platform_name</att>
        <att name="collected_beginning_date">none</att>
        <att name="platform">vessel of opportunity</att>
    </addAttributes>
    <dataVariable>
        <sourceName>="Seaspan Royal"</sourceName>
        <destinationName>platform_name</destinationName>
        <dataType>String</dataType>
        <!-- sourceAttributes>
        <att name="calendar">proleptic_gregorian</att>
        <att name="units">seconds since 2022-06-13 17:11:54</att>
    </sourceAttributes -->
        <addAttributes>
            <att name="long_name">Platform Name</att>
            <att name="standard_name">platform_name</att>
            <att name="cf_role">trajectory_id</att>
        </addAttributes>
    </dataVariable>
    <dataVariable>
        <sourceName>time</sourceName>
        <destinationName>time</destinationName>
        <dataType>long</dataType>
        <!-- sourceAttributes>
        <att name="calendar">proleptic_gregorian</att>
        <att name="units">seconds since 2022-06-13 17:11:54</att>
    </sourceAttributes -->
        <addAttributes>
            <att name="_FillValue" type="long">9223372036854775807</att>
            <att name="long_name">Time</att>
            <att name="standard_name">time</att>
            <att name="units">seconds since 1970-01-01T00:00:00Z</att>
        </addAttributes>
    </dataVariable>
    <dataVariable>
        <sourceName>latitude_degrees_north</sourceName>
        <destinationName>latitude</destinationName>
        <dataType>double</dataType>
        <!-- sourceAttributes>
        <att name="_FillValue" type="double">NaN</att>
        <att name="long_name">Latitude</att>
    </sourceAttributes -->
        <addAttributes>
            <att name="colorBarMaximum" type="double">90.0</att>
            <att name="colorBarMinimum" type="double">-90.0</att>
            <att name="missing_value" type="double">NaN</att>
            <att name="source_name">latitude_degrees_north</att>
            <att name="standard_name">latitude</att>
            <att name="units">degrees_north</att>
        </addAttributes>
    </dataVariable>
    <dataVariable>
        <sourceName>longitude_degrees_east</sourceName>
        <destinationName>longitude</destinationName>
        <dataType>double</dataType>
        <!-- sourceAttributes>
        <att name="_FillValue" type="double">NaN</att>
        <att name="long_name">Longitude</att>
    </sourceAttributes -->
        <addAttributes>
            <att name="colorBarMaximum" type="double">180.0</att>
            <att name="colorBarMinimum" type="double">-180.0</att>
            <att name="missing_value" type="double">NaN</att>
            <att name="source_name">longitude_degrees_east</att>
            <att name="standard_name">longitude</att>
            <att name="units">degrees_east</att>
        </addAttributes>
    </dataVariable>
    <dataVariable>
        <sourceName>gps_datetime</sourceName>
        <destinationName>gps_datetime</destinationName>
        <dataType>double</dataType>
        <!-- sourceAttributes>
        <att name="_FillValue" type="double">NaN</att>
        <att name="calendar">proleptic_gregorian</att>
        <att name="long_name">GPS Time</att>
        <att name="units">seconds since 2022-06-30T23:59:54</att>
    </sourceAttributes -->
        <addAttributes>
            <att name="missing_value" type="double">0</att>
            <att name="long_name">GPS Time</att>
            <att name="units">seconds since 1970-01-01T00:00:00Z</att>
        </addAttributes>
    </dataVariable>
    <dataVariable>
        <sourceName>b_pressure_inch</sourceName>
        <destinationName>b_pressure_inch</destinationName>
        <dataType>double</dataType>
        <!-- sourceAttributes>
        <att name="_FillValue" type="double">NaN</att>
        <att name="long_name">Barometric pressure, inches of mercury</att>
    </sourceAttributes -->
        <addAttributes>
            <att name="colorBarMaximum" type="double">1050.0</att>
            <att name="colorBarMinimum" type="double">950.0</att>
            <att name="missing_value" type="double">NaN</att>
            <att name="standard_name">air_pressure</att>
            <att name="units">inHg</att>
        </addAttributes>
    </dataVariable>
    <dataVariable>
        <sourceName>b_pressure_bar</sourceName>
        <destinationName>b_pressure_bar</destinationName>
        <dataType>double</dataType>
        <!-- sourceAttributes>
        <att name="_FillValue" type="double">NaN</att>
            <att name="long_name">Barometric pressure, bars</att>
        </sourceAttributes -->
        <addAttributes>
            <att name="colorBarMaximum" type="double">1050.0</att>
            <att name="colorBarMinimum" type="double">950.0</att>
            <att name="missing_value" type="double">NaN</att>
            <att name="standard_name">air_pressure</att>
            <att name="units">Bar</att>
        </addAttributes>
    </dataVariable>
    <dataVariable>
        <sourceName>air_temp</sourceName>
        <destinationName>air_temp</destinationName>
        <dataType>double</dataType>
        <!-- sourceAttributes>
        <att name="_FillValue" type="double">NaN</att>
        <att name="long_name">Air temperature, degrees C</att>
    </sourceAttributes -->
        <addAttributes>
            <att name="missing_value" type="double">NaN</att>
        </addAttributes>
    </dataVariable>
    <dataVariable>
        <sourceName>rel_humidity</sourceName>
        <destinationName>rel_humidity</destinationName>
        <dataType>double</dataType>
        <!-- sourceAttributes>
        <att name="_FillValue" type="double">NaN</att>
        <att name="long_name">Air temperature, degrees C</att>
    </sourceAttributes -->
        <addAttributes>
            <att name="missing_value" type="double">NaN</att>
            <att name="long_name"> Relative Humidity</att>
            <att name="standard_name">relative_humidity</att>
            <att name="units">percent</att>
        </addAttributes>
    </dataVariable>
    <dataVariable>
        <sourceName>spd_over_grnd</sourceName>
        <destinationName>spd_over_grnd</destinationName>
        <dataType>double</dataType>
        <!-- sourceAttributes>
        <att name="_FillValue" type="double">NaN</att>
        <att name="long_name">Speed Over Ground</att>
    </sourceAttributes -->
        <addAttributes>
            <att name="missing_value" type="double">NaN</att>
            <att name="long_name">Platform Speed Over Ground</att>
            <att name="units">knots</att>
            <att name="standard_name">platform_speed_wrt_ground</att>
        </addAttributes>
    </dataVariable>
    <dataVariable>
        <sourceName>true_course</sourceName>
        <destinationName>true_course</destinationName>
        <dataType>double</dataType>
        <!-- sourceAttributes>
        <att name="_FillValue" type="double">NaN</att>
        <att name="long_name">True Course</att>
    </sourceAttributes -->
        <addAttributes>
            <att name="missing_value" type="double">NaN</att>
            <att name="long_name">Platform True Course</att>
            <att name="units">degrees</att>
            <att name="standard_name">platform_course</att>
        </addAttributes>
    </dataVariable>

    <dataVariable>
        <sourceName>wind_speed_relative_to_platform_knots</sourceName>
        <destinationName>wind_speed_relative_to_platform_knots</destinationName>
        <dataType>double</dataType>
        <!-- sourceAttributes>
        <att name="_FillValue" type="double">NaN</att>
        <att name="long_name">Wind Speed Relative To Platform [knots]</att>
    </sourceAttributes -->
        <addAttributes>
            <att name="colorBarMaximum" type="double">15.0</att>
            <att name="colorBarMinimum" type="double">0.0</att>
            <att name="missing_value" type="double">NaN</att>
            <att name="units">knots</att>
        </addAttributes>
    </dataVariable>
    <dataVariable>
        <sourceName>wind_direction_relative_to_platform</sourceName>
        <destinationName>wind_direction_relative_to_platform</destinationName>
        <dataType>double</dataType>
        <!-- sourceAttributes>
        <att name="_FillValue" type="double">NaN</att>
        <att name="long_name">Wind Direction Relative To Platform</att>
    </sourceAttributes -->
        <addAttributes>
            <att name="colorBarMaximum" type="double">360.0</att>
            <att name="colorBarMinimum" type="double">0.0</att>
            <att name="missing_value" type="double">NaN</att>
            <att name="units">degrees</att>
        </addAttributes>
    </dataVariable>
    <dataVariable>
        <sourceName>heading</sourceName>
        <destinationName>heading</destinationName>
        <dataType>double</dataType>
        <!-- sourceAttributes>
        <att name="_FillValue" type="double">NaN</att>
        <att name="long_name">Heading</att>
    </sourceAttributes -->
        <addAttributes>
            <att name="missing_value" type="double">NaN</att>
            <att name="units">degrees</att>
            <att name="standard_name">platform_orientation</att>
        </addAttributes>
    </dataVariable>
    <dataVariable>
        <sourceName>corrected_wind_speed_knots</sourceName>
        <destinationName>corrected_wind_speed_knots</destinationName>
        <dataType>double</dataType>
        <!-- sourceAttributes>
        <att name="_FillValue" type="double">NaN</att>
    </sourceAttributes -->
        <addAttributes>
            <att name="long_name">Wind From Direction</att>
            <att name="missing_value" type="double">NaN</att>
            <att name="standard_name">wind_speed</att>
            <att name="units">knots</att>
        </addAttributes>
    </dataVariable>
    <dataVariable>
        <sourceName>corrected_wind_direction</sourceName>
        <destinationName>corrected_wind_direction</destinationName>
        <dataType>double</dataType>
        <!-- sourceAttributes>
        <att name="_FillValue" type="double">NaN</att>
    </sourceAttributes -->
        <addAttributes>
            <att name="colorBarMaximum" type="double">360.0</att>
            <att name="colorBarMinimum" type="double">0.0</att>
            <att name="long_name">Wind From Direction</att>
            <att name="missing_value" type="double">NaN</att>
            <att name="standard_name">wind_from_direction</att>
            <att name="units">degrees</att>
        </addAttributes>
    </dataVariable>
    <dataVariable>
        <sourceName>CO2_ppm</sourceName>
        <destinationName>CO2_ppm</destinationName>
        <dataType>double</dataType>
        <!-- sourceAttributes>
        <att name="_FillValue" type="double">NaN</att>
    </sourceAttributes -->
        <addAttributes>
            <att name="missing_value" type="double">NaN</att>
            <att name="long_name">Raw CO2 mole Fractions in Dry Air</att>
            <att name="units">ppm</att>
        </addAttributes>
    </dataVariable>
    <dataVariable>
        <sourceName>CO2_abs</sourceName>
        <destinationName>CO2_abs</destinationName>
        <dataType>double</dataType>
        <!-- sourceAttributes>
        <att name="_FillValue" type="double">NaN</att>
    </sourceAttributes -->
        <addAttributes>
            <att name="missing_value" type="double">NaN</att>
            <att name="long_name">Raw CO2 Absorbance</att>
        </addAttributes>
    </dataVariable>
    <dataVariable>
        <sourceName>H2O_ppt_mass</sourceName>
        <destinationName>H2O_ppt_mass</destinationName>
        <dataType>double</dataType>
        <!-- sourceAttributes>
        <att name="_FillValue" type="double">NaN</att>
    </sourceAttributes -->
        <addAttributes>
            <att name="long_name">Raw H2O Channel Mole Fractions in Dry Air</att>
            <att name="missing_value" type="double">NaN</att>
            <att name="units">ppm</att>
        </addAttributes>
    </dataVariable>
    <dataVariable>
        <sourceName>H2Oabs</sourceName>
        <destinationName>H2Oabs</destinationName>
        <dataType>double</dataType>
        <!-- sourceAttributes>
        <att name="_FillValue" type="double">NaN</att>
    </sourceAttributes -->
        <addAttributes>
            <att name="long_name">Raw H2O Channel Absorbance</att>
            <att name="missing_value" type="double">NaN</att>
        </addAttributes>
    </dataVariable>
    <dataVariable>
        <sourceName>Cell_T</sourceName>
        <destinationName>Cell_T</destinationName>
        <dataType>double</dataType>
        <!-- sourceAttributes>
        <att name="_FillValue" type="double">NaN</att>
    </sourceAttributes -->
        <addAttributes>
            <att name="long_name">Cell T</att>
            <att name="missing_value" type="double">NaN</att>
            <att name="long_name">Cell Temperature</att>
            <att name="units">deg C</att>
        </addAttributes>
    </dataVariable>
    <dataVariable>
        <sourceName>Cell_P</sourceName>
        <destinationName>Cell_P</destinationName>
        <dataType>double</dataType>
        <!-- sourceAttributes>
        <att name="_FillValue" type="double">NaN</att>
        </sourceAttributes -->
        <addAttributes>
            <att name="long_name">Cell Pressure</att>
            <att name="missing_value" type="double">NaN</att>
            <att name="units">mbar</att>
        </addAttributes>
    </dataVariable>
    <dataVariable>
        <sourceName>820pwr</sourceName>
        <destinationName>a_820pwr</destinationName>
        <dataType>double</dataType>
        <!-- sourceAttributes>
        <att name="_FillValue" type="double">NaN</att>
    </sourceAttributes -->
        <addAttributes>
            <att name="long_name">820PWR</att>
            <att name="missing_value" type="double">NaN</att>
        </addAttributes>
    </dataVariable>
    <dataVariable>
        <sourceName>Fluke_Temp</sourceName>
        <destinationName>Fluke_Temp</destinationName>
        <dataType>double</dataType>
        <!-- sourceAttributes>
        <att name="_FillValue" type="double">NaN</att>
    </sourceAttributes -->
        <addAttributes>
            <att name="long_name">Fluke Temperature</att>
            <att name="units">deg C</att>
        </addAttributes>
    </dataVariable>
    <dataVariable>
        <sourceName>Press_kPa</sourceName>
        <destinationName>Press_kPa</destinationName>
        <dataType>double</dataType>
        <!-- sourceAttributes>
        <att name="_FillValue" type="double">NaN</att>
    </sourceAttributes -->
        <addAttributes>
            <att name="long_name">Pressure</att>
            <att name="missing_value" type="double">NaN</att>
            <att name="units">kPa</att>
        </addAttributes>
    </dataVariable>
    <dataVariable>
        <sourceName>SB63_T</sourceName>
        <destinationName>SB63_T</destinationName>
        <dataType>double</dataType>
        <!-- sourceAttributes>
        <att name="_FillValue" type="double">NaN</att>
    </sourceAttributes -->
        <addAttributes>
            <att name="long_name">Oxygen Sensor Temperature</att>
            <att name="units">deg C</att>
            <att name="standard_name">temperature_of_sensor_for_oxygen_in_sea_water</att>
        </addAttributes>
    </dataVariable>
    <dataVariable>
        <sourceName>SB63_O2</sourceName>
        <destinationName>SB63_O2</destinationName>
        <dataType>double</dataType>
        <!-- sourceAttributes>
        <att name="_FillValue" type="double">NaN</att>
    </sourceAttributes -->
        <addAttributes>
            <att name="long_name">Dissolved oxygen Concentration</att>
            <att name="units">mL/L</att>
            <att name="standard_name">volume_fraction_of_oxygen_in_sea_water</att>
        </addAttributes>
    </dataVariable>
    <dataVariable>
        <sourceName>SB63_RawP</sourceName>
        <destinationName>SB63_RawP</destinationName>
        <dataType>double</dataType>
        <!-- sourceAttributes>
        <att name="_FillValue" type="double">NaN</att>
    </sourceAttributes -->
        <addAttributes>
            <att name="long_name">SB63 Raw Phase</att>
        </addAttributes>
    </dataVariable>
    <dataVariable>
        <sourceName>SB63_RawTV</sourceName>
        <destinationName>SB63_RawTV</destinationName>
        <dataType>double</dataType>
        <!-- sourceAttributes>
        <att name="_FillValue" type="double">NaN</att>
    </sourceAttributes -->
        <addAttributes>
            <att name="long_name">SB63 Raw Temperature Voltage</att>
            <att name="units">Volt</att>
        </addAttributes>
    </dataVariable>
    <dataVariable>
        <sourceName>Press_V</sourceName>
        <destinationName>Press_V</destinationName>
        <dataType>double</dataType>
        <!-- sourceAttributes>
        <att name="_FillValue" type="double">NaN</att>
    </sourceAttributes -->
        <addAttributes>
            <att name="long_name">Pressure Voltage</att>
            <att name="missing_value" type="double">NaN</att>
            <att name="units">Volt</att>
        </addAttributes>
    </dataVariable>
    <dataVariable>
        <sourceName>IO1</sourceName>
        <destinationName>IO1</destinationName>
        <dataType>double</dataType>
        <!-- sourceAttributes>
        <att name="_FillValue" type="double">NaN</att>
    </sourceAttributes -->
        <addAttributes>
            <att name="long_name">IO1</att>
            <att name="missing_value" type="double">NaN</att>
        </addAttributes>
    </dataVariable>
    <dataVariable>
        <sourceName>IO2</sourceName>
        <destinationName>IO2</destinationName>
        <dataType>double</dataType>
        <!-- sourceAttributes>
        <att name="_FillValue" type="double">NaN</att>
    </sourceAttributes -->
        <addAttributes>
            <att name="long_name">IO2</att>
        </addAttributes>
    </dataVariable>
    <dataVariable>
        <sourceName>IO3</sourceName>
        <destinationName>IO3</destinationName>
        <dataType>double</dataType>
        <!-- sourceAttributes>
        <att name="_FillValue" type="double">NaN</att>
    </sourceAttributes -->
        <addAttributes>
            <att name="long_name">IO3</att>
            <att name="missing_value" type="double">NaN</att>
        </addAttributes>
    </dataVariable>
    <dataVariable>
        <sourceName>Valve1pos</sourceName>
        <destinationName>Valve1pos</destinationName>
        <dataType>double</dataType>
        <!-- sourceAttributes>
        <att name="_FillValue" type="double">NaN</att>
    </sourceAttributes -->
        <addAttributes>
            <att name="long_name">Valve1pos</att>
        </addAttributes>
    </dataVariable>
    <dataVariable>
        <sourceName>StandardVal</sourceName>
        <destinationName>StandardVal</destinationName>
        <dataType>long</dataType>
        <!-- sourceAttributes>
    </sourceAttributes -->
        <addAttributes>
            <att name="_FillValue" type="long">9223372036854775807</att>
            <att name="long_name">Standard Val</att>
        </addAttributes>
    </dataVariable>
    <dataVariable>
        <sourceName>TSG_T</sourceName>
        <destinationName>TSG_T</destinationName>
        <dataType>double</dataType>
        <!-- sourceAttributes>
        <att name="_FillValue" type="double">NaN</att>
    </sourceAttributes -->
        <addAttributes>
            <att name="long_name">TSG Temperature</att>
            <att name="units">deg C</att>
            <att name="standard_name">sea_surface_temperature</att>
        </addAttributes>
    </dataVariable>
    <dataVariable>
        <sourceName>TSG_Cond</sourceName>
        <destinationName>TSG_Cond</destinationName>
        <dataType>double</dataType>
        <!-- sourceAttributes>
        <att name="_FillValue" type="double">NaN</att>
    </sourceAttributes -->
        <addAttributes>
            <att name="long_name">TSG Conductivity</att>
            <att name="missing_value" type="double">NaN</att>
            <att name="units">S/m</att>
            <att name="standard_name">sea_water_electrical_conductivity</att>
        </addAttributes>
    </dataVariable>
    <dataVariable>
        <sourceName>TSG_Sal</sourceName>
        <destinationName>TSG_Sal</destinationName>
        <dataType>double</dataType>
        <!-- sourceAttributes>
        <att name="_FillValue" type="double">NaN</att>
    </sourceAttributes -->
        <addAttributes>
            <att name="long_name">TSG Salinity</att>
            <att name="missing_value" type="double">NaN</att>
            <att name="units">1e-3</att>
            <att name="scale">PSS-78</att>
            <att name="standard_name">sea_surface_salinity</att>
        </addAttributes>
    </dataVariable>
    <dataVariable>
        <sourceName>Remote_Therm</sourceName>
        <destinationName>Remote_Therm</destinationName>
        <dataType>double</dataType>
        <!-- sourceAttributes>
        <att name="_FillValue" type="double">NaN</att>
    </sourceAttributes -->
        <addAttributes>
            <att name="long_name">Remote Therm</att>
            <att name="missing_value" type="double">NaN</att>
        </addAttributes>
    </dataVariable>


</dataset>